invenio_pidrelations/__init__.py
invenio_pidrelations/api.py
invenio_pidrelations/config.py
invenio_pidrelations/errors.py
invenio_pidrelations/ext.py
invenio_pidrelations/indexers.py
invenio_pidrelations/models.py
invenio_pidrelations/proxies.py
invenio_pidrelations/utils.py
invenio_pidrelations/version.py
invenio_pidrelations/alembic/1d4e361b7586_create_pidrelations_tables.py
invenio_pidrelations/alembic/2216c32d7059_create_pidrelations_branch.py
invenio_pidrelations/contrib/__init__.py
invenio_pidrelations/contrib/draft.py
invenio_pidrelations/contrib/search.py
invenio_pidrelations/contrib/versioning.py
invenio_pidrelations/contrib/templates/invenio_pidrelations/macros/pid_versions.html
invenio_pidrelations/serializers/__init__.py
invenio_pidrelations/serializers/schemas.py
invenio_pidrelations/serializers/utils.py
invenio_pidrelations-1.0.0.dist-info/licenses/AUTHORS.rst
invenio_pidrelations-1.0.0.dist-info/licenses/LICENSE
invenio_pidrelations-1.0.0.dist-info/METADATA
invenio_pidrelations-1.0.0.dist-info/WHEEL
invenio_pidrelations-1.0.0.dist-info/entry_points.txt
invenio_pidrelations-1.0.0.dist-info/top_level.txt
invenio_pidrelations-1.0.0.dist-info/RECORD
