Metadata-Version: 2.4
Name: invenio-pidrelations
Version: 1.0.0
Summary: Invenio module that adds PID relations to the Invenio-PIDStore module.
Home-page: https://github.com/inveniosoftware/invenio-pidrelations
Author: CERN
Author-email: info@inveniosoftware.org
License: MIT
Keywords: invenio pidstore persistent identifier relations
Platform: any
Classifier: Environment :: Web Environment
Classifier: Intended Audience :: Developers
Classifier: License :: OSI Approved :: MIT License
Classifier: Operating System :: OS Independent
Classifier: Programming Language :: Python
Classifier: Topic :: Internet :: WWW/HTTP :: Dynamic Content
Classifier: Topic :: Software Development :: Libraries :: Python Modules
Classifier: Programming Language :: Python :: 3
Classifier: Programming Language :: Python :: 3.6
Classifier: Development Status :: 1 - Planning
Requires-Python: >=3.8
License-File: LICENSE
License-File: AUTHORS.rst
Requires-Dist: invenio-base>=1.2.3
Requires-Dist: invenio-i18n>=2.0.0
Requires-Dist: invenio-pidstore>=1.0.0
Requires-Dist: marshmallow<4.0.0,>=3.3.0
Requires-Dist: speaklater<2.0,>=1.3
Provides-Extra: docs
Requires-Dist: Sphinx>=5; extra == "docs"
Provides-Extra: elasticsearch7
Requires-Dist: invenio-search[elasticsearch7]<4.0.0,>=3.1.0; extra == "elasticsearch7"
Provides-Extra: opensearch2
Requires-Dist: invenio-search[opensearch2]<4.0.0,>=3.1.0; extra == "opensearch2"
Provides-Extra: tests
Requires-Dist: pytest-invenio>=3.4.2; extra == "tests"
Requires-Dist: pytest-black>=0.3.0; extra == "tests"
Requires-Dist: invenio-app<3.0.0,>=2.0.0; extra == "tests"
Requires-Dist: pytest-mock>=1.6.0; extra == "tests"
Requires-Dist: Sphinx>=5; extra == "tests"
Provides-Extra: mysql
Requires-Dist: invenio-db[mysql,versioning]<3.0.0,>=2.0.0; extra == "mysql"
Provides-Extra: postgresql
Requires-Dist: invenio-db[postgresql,versioning]<3.0.0,>=2.0.0; extra == "postgresql"
Provides-Extra: sqlite
Requires-Dist: invenio-db[versioning]<3.0.0,>=2.0.0; extra == "sqlite"
Provides-Extra: records
Requires-Dist: invenio-records>=2.2.1; extra == "records"
Requires-Dist: invenio-records-ui>=1.1.0; extra == "records"
Provides-Extra: indexer
Requires-Dist: invenio-indexer>=1.1.2; extra == "indexer"
Dynamic: license-file
